sigy/__init__.py
sigy/inject.py
sigy/introspect.py
sigy-0.0.2.dist-info/LICENSE
sigy-0.0.2.dist-info/WHEEL
sigy-0.0.2.dist-info/METADATA
sigy-0.0.2.dist-info/RECORD
